MANIFEST.in
README
distribute_setup.py
setup.py
GoogleAppEngineMapReduce.egg-info/PKG-INFO
GoogleAppEngineMapReduce.egg-info/SOURCES.txt
GoogleAppEngineMapReduce.egg-info/dependency_links.txt
GoogleAppEngineMapReduce.egg-info/requires.txt
GoogleAppEngineMapReduce.egg-info/top_level.txt
GoogleAppEngineMapReduce.egg-info/zip-safe
cloudstorage/__init__.py
cloudstorage/api_utils.py
cloudstorage/cloudstorage_api.py
cloudstorage/common.py
cloudstorage/errors.py
cloudstorage/rest_api.py
cloudstorage/storage_api.py
cloudstorage/test_utils.py
graphy/__init__.py
graphy/all_tests.py
graphy/bar_chart.py
graphy/bar_chart_test.py
graphy/common.py
graphy/common_test.py
graphy/formatters.py
graphy/formatters_test.py
graphy/graphy_test.py
graphy/line_chart.py
graphy/line_chart_test.py
graphy/pie_chart.py
graphy/pie_chart_test.py
graphy/util.py
graphy/backends/__init__.py
graphy/backends/google_chart_api/__init__.py
graphy/backends/google_chart_api/bar_chart_test.py
graphy/backends/google_chart_api/base_encoder_test.py
graphy/backends/google_chart_api/encoders.py
graphy/backends/google_chart_api/line_chart_test.py
graphy/backends/google_chart_api/pie_chart_test.py
graphy/backends/google_chart_api/util.py
graphy/backends/google_chart_api/util_test.py
mapreduce/__init__.py
mapreduce/base_handler.py
mapreduce/context.py
mapreduce/control.py
mapreduce/datastore_range_iterators.py
mapreduce/errors.py
mapreduce/handlers.py
mapreduce/hooks.py
mapreduce/include.yaml
mapreduce/input_readers.py
mapreduce/json_util.py
mapreduce/key_ranges.py
mapreduce/kv_pb.py
mapreduce/main.py
mapreduce/map_job_context.py
mapreduce/mapper_pipeline.py
mapreduce/mapreduce_pipeline.py
mapreduce/model.py
mapreduce/namespace_range.py
mapreduce/output_writers.py
mapreduce/parameters.py
mapreduce/pipeline_base.py
mapreduce/property_range.py
mapreduce/records.py
mapreduce/shard_life_cycle.py
mapreduce/shuffler.py
mapreduce/status.py
mapreduce/test_support.py
mapreduce/util.py
mapreduce/api/__init__.py
mapreduce/api/map_job/__init__.py
mapreduce/api/map_job/abstract_datastore_input_reader.py
mapreduce/api/map_job/datastore_input_reader.py
mapreduce/api/map_job/input_reader.py
mapreduce/api/map_job/map_job_config.py
mapreduce/api/map_job/map_job_control.py
mapreduce/api/map_job/mapper.py
